microsoft/teams/openai/__init__.py
microsoft/teams/openai/common.py
microsoft/teams/openai/completions_model.py
microsoft/teams/openai/function_utils.py
microsoft/teams/openai/responses_chat_model.py
microsoft_teams_openai-2.0.0a5.dist-info/METADATA
microsoft_teams_openai-2.0.0a5.dist-info/WHEEL
microsoft_teams_openai-2.0.0a5.dist-info/RECORD
