Metadata-Version: 2.4
Name: microsoft-teams-openai
Version: 2.0.0a5
Summary: model package for enabling chat experiences with openai
Author-email: Microsoft <TeamsAISDKFeedback@microsoft.com>
License-Expression: MIT
Keywords: agents,ai,bot,microsoft,teams
Requires-Python: <3.14,>=3.12
Requires-Dist: microsoft-teams-ai
Requires-Dist: microsoft-teams-common
Requires-Dist: openai>=2.4.0
Requires-Dist: python-dotenv
